spynl/cli/__init__.py
spynl/cli/bash.completion
spynl/cli/utils.py
spynl/cli/zsh.completion
spynl/cli/__pycache__/__init__.cpython-35.pyc
spynl/cli/__pycache__/utils.cpython-35.pyc
spynl/cli/dev/__init__.py
spynl/cli/dev/hg.py
spynl/cli/dev/merge_branch.sh
spynl/cli/dev/new_branch.sh
spynl/cli/dev/tasks.py
spynl/cli/dev/__pycache__/__init__.cpython-35.pyc
spynl/cli/dev/__pycache__/tasks.cpython-35.pyc
spynl/cli/ops/prepare-stage.sh
spynl/cli/ops/run-unit-tests.sh
spynl/cli/ops/tasks.py
spynl/cli/ops/__pycache__/tasks.cpython-35.pyc
spynl/cli/ops/docker/Dockerfile
spynl/cli/ops/docker/build-image.sh
spynl/cli/ops/docker/run.sh
spynl/cli/ops/docker/setup.sh
spynl/cli/ops/docker/supervisord.conf
spynl/main/__init__.py
spynl/main/dateutils.py
spynl/main/endpoints.py
spynl/main/error_views.py
spynl/main/events.py
spynl/main/exceptions.py
spynl/main/mail.py
spynl/main/pkg_utils.py
spynl/main/plugins.py
spynl/main/routing.py
spynl/main/session.py
spynl/main/testutils.py
spynl/main/urlson.py
spynl/main/utils.py
spynl/main/validation.py
spynl/main/version.py
spynl/main/__pycache__/__init__.cpython-35.pyc
spynl/main/__pycache__/dateutils.cpython-35.pyc
spynl/main/__pycache__/endpoints.cpython-35.pyc
spynl/main/__pycache__/error_views.cpython-35.pyc
spynl/main/__pycache__/events.cpython-35.pyc
spynl/main/__pycache__/exceptions.cpython-35.pyc
spynl/main/__pycache__/mail.cpython-35.pyc
spynl/main/__pycache__/pkg_utils.cpython-35.pyc
spynl/main/__pycache__/plugins.cpython-35.pyc
spynl/main/__pycache__/routing.cpython-35.pyc
spynl/main/__pycache__/session.cpython-35.pyc
spynl/main/__pycache__/testutils.cpython-35.pyc
spynl/main/__pycache__/urlson.cpython-35.pyc
spynl/main/__pycache__/utils.cpython-35.pyc
spynl/main/__pycache__/validation.cpython-35.pyc
spynl/main/__pycache__/version.cpython-35.pyc
spynl/main/about/__init__.py
spynl/main/about/endpoints.py
spynl/main/about/__pycache__/__init__.cpython-35.pyc
spynl-6.0.1.dist-info/DESCRIPTION.rst
spynl-6.0.1.dist-info/METADATA
spynl-6.0.1.dist-info/RECORD
spynl-6.0.1.dist-info/WHEEL
spynl-6.0.1.dist-info/entry_points.txt
spynl-6.0.1.dist-info/metadata.json
spynl-6.0.1.dist-info/paster_plugins.txt
spynl-6.0.1.dist-info/top_level.txt
